shlack/__init__.py
shlack/__main__.py
shlack/runner.py
shlack/slack.py
shlack/cli/__init__.py
shlack/cli/__main__.py
shlack/cli/message.py
shlack/cli/task.py
shlack-0.1.1.dist-info/METADATA
shlack-0.1.1.dist-info/WHEEL
shlack-0.1.1.dist-info/entry_points.txt
shlack-0.1.1.dist-info/top_level.txt
shlack-0.1.1.dist-info/RECORD
