Metadata-Version: 2.1
Name: shlack
Version: 0.1.1
Summary: Yet another slack command line interface.
Home-page: https://github.com/nolanbconaway/shlack
Author: Nolan Conaway
Author-email: nolanbconaway@gmail.com
License: MIT
Keywords: slack,cli
Platform: UNKNOWN
Classifier: Operating System :: MacOS
Classifier: Operating System :: Unix
Classifier: Operating System :: POSIX
Classifier: Programming Language :: Python :: 2.7
Classifier: Programming Language :: Python :: 3.5
Classifier: Programming Language :: Python :: 3.6
Classifier: Programming Language :: Python :: 3.7
Requires-Dist: slacker
Requires-Dist: click
